espo/__init__.py
espo/client.py
espo/exceptions.py
espo/types.py
espo-0.1.0.dist-info/LICENSE
espo-0.1.0.dist-info/METADATA
espo-0.1.0.dist-info/WHEEL
espo-0.1.0.dist-info/RECORD
