Metadata-Version: 2.1
Name: espo
Version: 0.1.0
Summary: Python client for EspoCRM
License: MIT
Author: Ivan Fedorov
Author-email: i@ifedorov.me
Requires-Python: >=3.10,<4.0
Classifier: License :: OSI Approved :: MIT License
Classifier: Programming Language :: Python :: 3
Classifier: Programming Language :: Python :: 3.10
Classifier: Programming Language :: Python :: 3.11
Classifier: Programming Language :: Python :: 3.12
Requires-Dist: requests (>=2.31.0,<3.0.0)
